dc_logger/__init__.py
dc_logger/_modidx.py
dc_logger/color_utils.py
dc_logger/decorators.py
dc_logger/logger.py
dc_logger/utils.py
dc_logger/client/__init__.py
dc_logger/client/base.py
dc_logger/client/enums.py
dc_logger/client/exceptions.py
dc_logger/client/extractors.py
dc_logger/client/models.py
dc_logger/configs/__init__.py
dc_logger/configs/base.py
dc_logger/configs/cloud.py
dc_logger/configs/console.py
dc_logger/configs/factory.py
dc_logger/configs/multi_handler.py
dc_logger/handlers/__init__.py
dc_logger/handlers/base.py
dc_logger/handlers/console.py
dc_logger/handlers/file.py
dc_logger/handlers/cloud/__init__.py
dc_logger/handlers/cloud/aws.py
dc_logger/handlers/cloud/azure.py
dc_logger/handlers/cloud/base.py
dc_logger/handlers/cloud/datadog.py
dc_logger/handlers/cloud/gcp.py
dc_logger/logs/__init__.py
dc_logger/logs/services/__init__.py
dc_logger/logs/services/console.py
dc_logger/logs/services/file.py
dc_logger/logs/services/cloud/__init__.py
dc_logger/logs/services/cloud/datadog.py
dc_logger/services/__init__.py
dc_logger/services/base.py
dc_logger/services/cloud/__init__.py
dc_logger/services/cloud/base.py
dc_logger/services/cloud/datadog.py
dc_logger/services/console/__init__.py
dc_logger/services/console/base.py
dc_logger-1.1.1.dist-info/licenses/LICENSE
dc_logger-1.1.1.dist-info/METADATA
dc_logger-1.1.1.dist-info/WHEEL
dc_logger-1.1.1.dist-info/top_level.txt
dc_logger-1.1.1.dist-info/RECORD
