Metadata-Version: 2.4
Name: dc_logger
Version: 1.1.1
Summary: A flexible logging library with support for cloud providers, multi-tenancy, and structured logging
Author-email: Jae Wilson <jaewilson07@gmail.com>
License-Expression: MIT
Project-URL: Homepage, https://github.com/jaewilson07/dc_logger
Project-URL: Documentation, https://jaewilson07.github.io/dc_logger
Project-URL: Repository, https://github.com/jaewilson07/dc_logger
Project-URL: Issues, https://github.com/jaewilson07/dc_logger/issues
Keywords: logging,datadog,cloud,observability,structured-logging
Classifier: Development Status :: 5 - Production/Stable
Classifier: Intended Audience :: Developers
Classifier: Programming Language :: Python :: 3
Classifier: Programming Language :: Python :: 3.8
Classifier: Programming Language :: Python :: 3.9
Classifier: Programming Language :: Python :: 3.10
Classifier: Programming Language :: Python :: 3.11
Classifier: Programming Language :: Python :: 3.12
Classifier: Topic :: System :: Logging
Requires-Python: >=3.8
License-File: LICENSE
Requires-Dist: pydantic
Requires-Dist: typing-extensions
Requires-Dist: requests
Provides-Extra: dev
Requires-Dist: jupyter; extra == "dev"
Requires-Dist: pytest; extra == "dev"
Requires-Dist: pytest-cov; extra == "dev"
Requires-Dist: ruff; extra == "dev"
Requires-Dist: mypy; extra == "dev"
Requires-Dist: black; extra == "dev"
Requires-Dist: bandit; extra == "dev"
Requires-Dist: isort; extra == "dev"
Requires-Dist: pre-commit; extra == "dev"
Requires-Dist: nbstripout; extra == "dev"
Provides-Extra: datadog
Requires-Dist: datadog-api-client>=2.0.0; extra == "datadog"
Provides-Extra: all
Requires-Dist: dc_logger[datadog,dev]; extra == "all"
Dynamic: license-file
